Workbook

Sheet Inventario
A1: Producto | B1: Costo | C1: Unidades | D1: Precio | E1: Ventas | F1: Unidades restantes
A2: Camiseta de Portugal de Ronaldo | B2: 100000 | C2: 1 | D2: 200000 | E2: 1 | F2: =C2-E2 -> 0
A3: Camiseta de Argentina de Messi | B3: 100000 | C3: 1 | D3: 200000 | E3: 1 | F3: =C3-E3 -> 0
A4: Camiseta de Colombia de James | B4: 100000 | C4: 1 | D4: 200000 | E4: 1 | F4: =C4-E4 -> 0
A5: Camiseta de Noruega de Haaland | B5: 100000 | C5: 1 | D5: 200000 | E5: 1 | F5: =C5-E5 -> 0
A6: Camiseta de Millonarios de Falcao | B6: 100000 | C6: 1 | D6: 200000 | E6: 1 | F6: =C6-E6 -> 0
A7: Menu pollo pesto | B7: 9000 | C7: 8 | D7: 18000 | E7: 5 | F7: =C7-E7 -> 3
A8: Bowl Vegetariano | B8: 9000 | C8: 8 | D8: 18000 | E8: 8 | F8: =C8-E8 -> 0
A9: Almuerzo dulce | B9: 9000 | C9: 8 | D9: 18000 | E9: 3 | F9: =C9-E9 -> 5
A10: Baguette | B10: 1800 | C10: 5 | D10: 3600 | E10: 3 | F10: =C10-E10 -> 2
A11: Croissant | B11: 4500 | C11: 5 | D11: 9000 | E11: 4 | F11: =C11-E11 -> 1
A12: Pan de chocolate | B12: 5500 | C12: 5 | D12: 11000 | E12: 5 | F12: =C12-E12 -> 0

Sheet Analisis Estadistico
A1: Métrica | B1: Valor
A2: Total productos | B2: =COUNTA(Inventario!A2:A1000) -> 11
A3: Costo promedio | B3: =AVERAGE(Inventario!B2:B1000) -> 48981.818
A4: Precio promedio | B4: =AVERAGE(Inventario!D2:D1000) -> 97963.636
A5: Ventas totales | B5: =SUM(Inventario!E2:E1000) -> 33
A6: Inventario restante | B6: =SUM(Inventario!F2:F1000) -> 11
A7: Ganancia total | B7: =SUMPRODUCT((Inventario!D2:D1000-Inventario!B2:B1000),Inventario!E2:E1000) -> 694900
A8: Desv. estándar precio | B8: =_xludf.STDEV.S(Inventario!D2:D1000) -> #NAME?
A9: Mediana precio | B9: =MEDIAN(Inventario!D2:D1000) -> 18000
A11: Producto | B11: Precio
A12: =Inventario!A2 -> Camiseta de Portugal de Ronaldo | B12: =Inventario!D2 -> 200000
A13: =Inventario!A3 -> Camiseta de Argentina de Messi | B13: =Inventario!D3 -> 200000
A14: =Inventario!A4 -> Camiseta de Colombia de James | B14: =Inventario!D4 -> 200000
A15: =Inventario!A5 -> Camiseta de Noruega de Haaland | B15: =Inventario!D5 -> 200000
A16: =Inventario!A6 -> Camiseta de Millonarios de Falcao | B16: =Inventario!D6 -> 200000
A17: =Inventario!A7 -> Menu pollo pesto | B17: =Inventario!D7 -> 18000
A18: =Inventario!A8 -> Bowl Vegetariano | B18: =Inventario!D8 -> 18000
A19: =Inventario!A9 -> Almuerzo dulce | B19: =Inventario!D9 -> 18000
A20: =Inventario!A10 -> Baguette | B20: =Inventario!D10 -> 3600
A21: =Inventario!A11 -> Croissant | B21: =Inventario!D11 -> 9000
A22: =Inventario!A12 -> Pan de chocolate | B22: =Inventario!D12 -> 11000
A27: Producto | B27: Ventas
A28: =Inventario!A2 -> Camiseta de Portugal de Ronaldo | B28: =Inventario!E2 -> 1
A29: =Inventario!A3 -> Camiseta de Argentina de Messi | B29: =Inventario!E3 -> 1
A30: =Inventario!A4 -> Camiseta de Colombia de James | B30: =Inventario!E4 -> 1
A31: =Inventario!A5 -> Camiseta de Noruega de Haaland | B31: =Inventario!E5 -> 1
A32: =Inventario!A6 -> Camiseta de Millonarios de Falcao | B32: =Inventario!E6 -> 1
A33: =Inventario!A7 -> Menu pollo pesto | B33: =Inventario!E7 -> 5
A34: =Inventario!A8 -> Bowl Vegetariano | B34: =Inventario!E8 -> 8
A35: =Inventario!A9 -> Almuerzo dulce | B35: =Inventario!E9 -> 3
A36: =Inventario!A10 -> Baguette | B36: =Inventario!E10 -> 3
A37: =Inventario!A11 -> Croissant | B37: =Inventario!E11 -> 4
A38: =Inventario!A12 -> Pan de chocolate | B38: =Inventario!E12 -> 5
